Metadata-Version: 2.1
Name: drep
Version: 3.6.1
Summary: De-replication of microbial genomes assembled from multiple samples
Home-page: https://github.com/MrOlm/drep
Author: Matt Olm
Author-email: mattolm@berkeley.edu
License: MIT
Requires-Dist: numpy
Requires-Dist: pandas
Requires-Dist: seaborn
Requires-Dist: matplotlib
Requires-Dist: biopython
Requires-Dist: scikit-learn
Requires-Dist: tqdm
Requires-Dist: pytest
